Workbook

Sheet Activité
A1: Mois | C1: 1 | E1: 2 | G1: 3 | I1: 4 | K1: 5 | M1: 6 | O1: 7 | Q1: 8 | S1: 9 | U1: 10
A2: Séances à domicile | B2: Prix de vente (€) | C2: 38 | E2: 38 | G2: 40 | I2: 40 | K2: 40 | M2: 40 | O2: 40 | Q2: 40 | S2: 40 | U2: 40
B3: Durée de la séance (min) | C3: 50 | E3: 50 | G3: 45 | I3: 45 | K3: 45 | M3: 45 | O3: 45 | Q3: 45 | S3: 45 | U3: 45
B4: Boisson | C4: énergétique | E4: énergétique | G4: énergétique | I4: énergétique | K4: énergétique | M4: énergétique | O4: énergétique | Q4: énergétique | S4: énergétique | U4: énergétique
B5: Base clients actuelle | C5: 0 | E5: 62 | G5: 71 | I5: 77 | K5: 85 | M5: 160 | O5: 163 | Q5: 165 | S5: 161 | U5: 188
C6: Prév. | D6: Réel | E6: Prév. | F6: Réel | G6: Prév. | H6: Réel | I6: Prév. | J6: Réel | K6: Prév. | L6: Réel | M6: Prév. | N6: Réel | O6: Prév. | P6: Réel | Q6: Prév. | R6: Réel | S6: Prév. | T6: Réel | U6: Prév. | V6: Réel
B7: Perte de clients | E7: 6 | F7: 7 | G7: 7 | H7: 7 | I7: 7 | J7: 12 | K7: 8 | L7: 13 | M7: 16 | N7: 14 | O7: 16 | P7: 14 | Q7: 16 | R7: 19 | S7: 16 | T7: 9 | U7: 18 | V7: 14
B8: Nouveaux clients | C8: 60 | D8: 60 | E8: 15 | F8: 16 | G8: 13 | H8: 13 | I8: 10 | J8: 20 | K8: 10 | L8: 20 | M8: 7 | N8: 17 | O8: 15 | P8: 16 | Q8: 15 | R8: 15 | S8: 15 | T8: 36 | U8: 15 | V8: 25
A9: vos décisions | B9: Base client du mois | C9: =C5-C7+C8 -> 60 | D9: =C5-D7+D8 -> 60 | E9: =E5-E7+E8 -> 71 | F9: =E5-F7+F8 -> 71 | G9: =G5-G7+G8 -> 77 | H9: =G5-H7+H8 -> 77 | I9: =I5-I7+I8 -> 80 | J9: =I5-J7+J8 -> 85 | K9: =K5-K7+K8 -> 87 | L9: =K5-L7+L8 -> 92 | M9: =M5-M7+M8 -> 151 | N9: =M5-N7+N8 -> 163 | O9: =O5-O7+O8 -> 162 | P9: =O5-P7+P8 -> 165 | Q9: =Q5-Q7+Q8 -> 164 | R9: =Q5-R7+R8 -> 161 | S9: =S5-S7+S8 -> 160 | T9: =S5-T7+T8 -> 188 | U9: =U5-U7+U8 -> 185 | V9: =U5-V7+V8 -> 199
A10: résultats (à reporter depuis l'onglet "Résultats de Startero) | B10: Panier moyen | C10: 2 | D10: 2 | E10: 2 | F10: 1.8 | G10: 1.8 | H10: 1.74 | I10: 1.7 | J10: 1.72 | K10: 1.7 | L10: 1.74 | M10: 1.7 | N10: 1.76 | O10: 1.8 | P10: 1.77 | Q10: 1.8 | R10: 1.8 | S10: 1.8 | T10: 1.83 | U10: 1.8 | V10: 1.82
B11: Nb de ventes | C11: =ROUND(C9*C10,0) -> 120 | D11: =ROUND(D9*D10,0) -> 120 | E11: =ROUND(E9*E10,0) -> 142 | F11: =ROUND(F9*F10,0) -> 128 | G11: =ROUND(G9*G10,0) -> 139 | H11: =ROUND(H9*H10,0) -> 134 | I11: =ROUND(I9*I10,0) -> 136 | J11: =ROUND(J9*J10,0) -> 146 | ... V11: =ROUND(V9*V10,0) -> 362
B12: Chiffre d'affaires | C12: =C11*C2 -> 4560 | D12: =D11*C2 -> 4560 | E12: =E11*E2 -> 5396 | F12: =F11*E2 -> 4864 | G12: =G11*G2 -> 5560 | H12: =H11*G2 -> 5360 | I12: =I11*I2 -> 5440 | J12: =J11*I2 -> 5840 | K12: =K11*K2 -> 5920 | L12: =L11*K2 -> 6400 | M12: =M11*M2 -> 10280 | N12: =N11*M2 -> 11480 | O12: =O11*O2 -> 11680 | P12: =P11*O2 -> 11680 | Q12: =Q11*Q2 -> 11800 | R12: =R11*Q2 -> 11600 | S12: =S11*S2 -> 11520 | T12: =T11*S2 -> 13760 | U12: =U11*U2 -> 13320 | V12: =V11*U2 -> 14480
B13: Part de marché | C13: 0.117 | E13: 0.108 | G13: 0.111 | I13: 0.11 | K13: 0.118 | M13: 0.129 | O13: 0.137 | Q13: 0.139 | S13: 0.14 | U13: 0.146
B14: Taux de service | C14: 1 | E14: 0.88 | G14: 0.9 | I14: 1 | K14: 1 | M14: 1 | O14: 1 | Q14: 1 | S14: 1 | U14: 1
B15: Satisfaction | C15: 80.3 | E15: 80.8 | G15: 80.3 | I15: 80.8 | K15: 81.2 | M15: 81.5 | O15: 81.9 | Q15: 82.2 | S15: 82.2 | U15: 82.4
A16: Séances collectives | B16: Prix de vente (€) | I16: 20 | K16: 20 | M16: 20 | O16: 17 | Q16: 16 | S16: 16 | U16: 16
B17: Durée de la séance (min) | I17: 60 | K17: 50 | M17: 65 | O17: 60 | Q17: 55 | S17: 55 | U17: 55
B18: Boisson | I18: eau | K18: eau | M18: eau | O18: eau | Q18: eau | S18: énergétique | U18: énergétique
B19: Base clients actuelle | I19: 0 | K19: 160 | M19: 220 | O19: 222 | Q19: 210 | S19: 223 | U19: 252
I20: Prév. | J20: Réel | K20: Prév. | L20: Réel | M20: Prév. | N20: Réel | O20: Prév. | P20: Réel | Q20: Prév. | R20: Réel | S20: Prév. | T20: Réel | U20: Prév. | V20: Réel
B21: Perte de clients | K21: 9 | L21: 11 | M21: 22 | N21: 18 | O21: 22 | P21: 20 | Q21: 21 | R21: 18 | S21: 18 | T21: 20 | U21: 20 | V21: 20
B22: Nouveaux clients | I22: 50 | J22: 160 | K22: 15 | L22: 71 | M22: 10 | N22: 20 | O22: 15 | P22: 8 | Q22: 15 | R22: 31 | S22: 15 | T22: 49 | U22: 15 | V22: 28
A23: vos décisions | B23: Base client du mois | I23: =I19-I21+I22 -> 50 | J23: =I19-J21+J22 -> 160 | K23: =K19-K21+K22 -> 166 | L23: =K19-L21+L22 -> 220 | M23: =M19-M21+M22 -> 208 | N23: =M19-N21+N22 -> 222 | O23: =O19-O21+O22 -> 215 | P23: =O19-P21+P22 -> 210 | Q23: =Q19-Q21+Q22 -> 204 | R23: =Q19-R21+R22 -> 223 | S23: =S19-S21+S22 -> 220 | T23: =S19-T21+T22 -> 252 | U23: =U19-U21+U22 -> 247 | V23: =U19-V21+V22 -> 260
A24: résultats (à reporter depuis l'onglet "Résultats de Startero) | B24: Panier moyen | I24: 1.5 | J24: 1.19 | K24: 1.19 | L24: 1.22 | M24: 1.22 | N24: 1.25 | O24: 1.25 | P24: 1.16 | Q24: 1.16 | R24: 1.24 | S24: 1.24 | T24: 1.3 | U24: 1.3 | V24: 1.31
B25: Nb de ventes | I25: =ROUND(I23*I24,0) -> 75 | J25: =ROUND(J23*J24,0) -> 190 | K25: =ROUND(K23*K24,0) -> 198 | L25: =ROUND(L23*L24,0) -> 268 | M25: =ROUND(M23*M24,0) -> 254 | N25: =ROUND(N23*N24,0) -> 278 | O25: =ROUND(O23*O24,0) -> 269 | P25: =ROUND(P23*P24,0) -> 244 | ... V25: =ROUND(V23*V24,0) -> 341
B26: Chiffre d'affaires | I26: =I25*I16 -> 1500 | J26: =J25*I16 -> 3800 | K26: =K25*K16 -> 3960 | L26: =L25*K16 -> 5360 | M26: =M25*M16 -> 5080 | N26: =N25*M16 -> 5560 | O26: =O25*O16 -> 4573 | P26: =P25*O16 -> 4148 | Q26: =Q25*Q16 -> 3792 | R26: =R25*Q16 -> 4432 | S26: =S25*S16 -> 4368 | T26: =T25*S16 -> 5248 | U26: =U25*U16 -> 5136 | V26: =V25*U16 -> 5456
B27: Part de marché | I27: 0.078 | K27: 0.097 | M27: 0.093 | O27: 0.079 | Q27: 0.088 | S27: 0.099 | U27: 0.102
B28: Taux de service | I28: 1 | K28: 1 | M28: 0.88 | O28: 0.81 | Q28: 1 | S28: 1 | U28: 0.95
B29: Satisfaction | I29: 73.8 | K29: 73.9 | M29: 72.3 | O29: 72.5 | Q29: 73 | S29: 74.2 | U29: 74.7
A31: Il y des calculs automatiques en place dans les cellules où la police d'écriture est bleue

Sheet Temps
B1: Mois | D1: 1 | F1: 2 | H1: 3 | J1: 4 | L1: 5 | N1: 6
B2: Antoine | C2: Temps disponible (h) | D2: =Paramètres!$C$14 -> 40 | F2: =Paramètres!$C$14 -> 40 | H2: =Paramètres!$C$14 -> 40 | J2: =Paramètres!$C$14 -> 40 | L2: =Paramètres!$C$14 -> 40 | N2: =Paramètres!$C$14 -> 40
B3: Administratif | C3: quotidien | D3: 10 | F3: 10 | H3: 10 | J3: 10 | L3: 10 | N3: 10
C4: communication | D4: 4 | F4: 12 | H4: 24 | J4: 24 | L4: 20 | N4: =6+18 -> 24
C5: études de marché | D5: 4 | F5: 4 | H5: 4 | J5: 4 | L5: 6 | N5: 6
C6: achat de matériel | D6: 4 | F6: 0 | H6: 0 | J6: 0 | L6: 4 | N6: 0
C7: divers | D7: 15 | F7: 0 | H7: 0 | J7: 0 | L7: 0 | N7: 0
A8: vos décisions | C8: Restant | D8: =MAX(D2-SUM(D3:E7),0) -> 3 | F8: =MAX(F2-SUM(F3:G7),0) -> 14 | H8: =MAX(H2-SUM(H3:I7),0) -> 2 | J8: =MAX(J2-SUM(J3:K7),0) -> 2 | L8: =MAX(L2-SUM(L3:M7),0) -> 0 | N8: =MAX(N2-SUM(N3:O7),0) -> 0
A9: résultats (à reporter depuis l'onglet "Résultats de Startero) | C9: Productivité | D9: =D2/D2 -> 1 | F9: =F2/F2 -> 1 | H9: =H2/H2 -> 1 | J9: =J2/J2 -> 1 | L9: =L2/L2 -> 1 | N9: =N2/N2 -> 1
C10: Occupation | D10: =IF(D2<>0,(D2-D8)/D2,0) -> 0.925 | F10: =IF(F2<>0,(F2-F8)/F2,0) -> 0.65 | H10: =IF(H2<>0,(H2-H8)/H2,0) -> 0.95 | J10: =IF(J2<>0,(J2-J8)/J2,0) -> 0.95 | L10: =IF(L2<>0,(L2-L8)/L2,0) -> 1 | N10: =IF(N2<>0,(N2-N8)/N2,0) -> 1
B11: Tess | C11: Temps disponible (h) | D11: =Paramètres!$C$15 -> 120 | F11: =Paramètres!$C$15 -> 120 | H11: =Paramètres!$C$15 -> 120 | J11: =Paramètres!$C$15 -> 120 | L11: =Paramètres!$C$15 -> 120 | N11: =Paramètres!$C$15 -> 120
C12: Moyen de déplacement | D12: Transports en commun | J12: Transports en commun
D13: Prév. | E13: Réel | F13: Prév. | G13: Réel | H13: Prév. | I13: Réel | J13: Prév. | K13: Réel | L13: Prév. | M13: Réel | N13: Prév. | O13: Réel
C14: Déplacement | D14: =VLOOKUP($D$12,Paramètres!$F$14:$G$16,2,FALSE)*Activité!C11/60 -> 16 | E14: =VLOOKUP($D$12,Paramètres!$F$14:$G$16,2,FALSE)*Activité!D11/60 -> 16 | F14: =VLOOKUP($D$12,Paramètres!$F$14:$G$16,2,FALSE)*Activité!E11/60 -> 18.933333 | G14: =VLOOKUP($D$12,Paramètres!$F$14:$G$16,2,FALSE)*Activité!F11/60 -> 17.066667 | H14: =VLOOKUP($D$12,Paramètres!$F$14:$G$16,2,FALSE)*Activité!G11/60 -> 18.533333 | I14: =VLOOKUP($D$12,Paramètres!$F$14:$G$16,2,FALSE)*Activité!H11/60 -> 17.866667 | J14: =VLOOKUP($J$12,Paramètres!$F$14:$G$16,2,FALSE)*Activité!I11/60 -> 18.133333 | K14: =VLOOKUP($J$12,Paramètres!$F$14:$G$16,2,FALSE)*Activité!J11/60 -> 19.466667 | L14: =VLOOKUP($J$12,Paramètres!$F$14:$G$16,2,FALSE)*Activité!K11/60 -> 19.733333 | M14: =VLOOKUP($J$12,Paramètres!$F$14:$G$16,2,FALSE)*Activité!L11/60 -> 21.333333 | N14: =VLOOKUP($J$12,Paramètres!$F$14:$G$16,2,FALSE)*Activité!M11/60 -> 34.266667 | O14: =VLOOKUP($J$12,Paramètres!$F$14:$G$16,2,FALSE)*Activité!N11/60 -> 38.266667
B15: Administratif | C15: Dépassement capacité Antoine | D15: =MAX(SUM(D3:E7)-D2,0) -> 0 | F15: =MAX(SUM(F3:G7)-F2,0) -> 0 | H15: =MAX(SUM(H3:I7)-H2,0) -> 0 | J15: =MAX(SUM(J3:K7)-J2,0) -> 0 | L15: =MAX(SUM(L3:M7)-L2,0) -> 0 | N15: =MAX(SUM(N3:O7)-N2,0) -> 0
C16: Accompagnement Salariés | J16: 20 | K16: 10 | L16: 10 | M16: 10 | N16: 12 | O16: 10
C17: Temps sportif utilisable | D17: =D11-D14-D15 -> 104 | E17: =D11-E14-D15 -> 104 | F17: =F11-F14-F15 -> 101.06667 | G17: =F11-G14-F15 -> 102.93333 | H17: =H11-H14-H15 -> 101.46667 | I17: =H11-I14-H15 -> 102.13333 | J17: =J11-J14-J15 -> 101.86667 | K17: =J11-K14-J15 -> 100.53333 | L17: =L11-L14-L15 -> 100.26667 | M17: =L11-M14-L15 -> 98.666667 | N17: =N11-N14-N15 -> 85.733333 | O17: =N11-O14-N15 -> 81.733333
B18: Sportif | C18: Séances à domicile | D18: =Activité!C3*Activité!C11 /60 -> 100 | E18: =Activité!C3*Activité!D11 /60 -> 100 | F18: =Activité!E3*Activité!E11 /60 -> 118.33333 | G18: =Activité!E3*Activité!F11 /60 -> 106.66667 | H18: =Activité!G3*Activité!G11 /60 -> 104.25 | I18: =Activité!G3*Activité!H11 /60 -> 100.5 | J18: =Activité!I3*Activité!I11 /60 -> 102 | K18: =Activité!I3*Activité!J11 /60 -> 109.5 | L18: =Activité!K3*Activité!K11 /60 -> 111 | M18: =Activité!K3*Activité!L11 /60 -> 120 | N18: =Activité!M3*Activité!M11 /60 -> 192.75 | O18: =Activité!M3*Activité!N11 /60 -> 215.25
C19: Restant | D19: =D17-D18 -> 4 | E19: =E17-E18 -> 4 | F19: =F17-F18 -> -17.266667 | G19: =G17-G18 -> -3.7333333 | H19: =H17-H18 -> -2.7833333 | I19: =I17-I18 -> 1.6333333 | J19: =J17-J18 -> -0.13333333 | K19: =K17-K18 -> -8.9666667 | ... O19: =O17-O18 -> -133.51667
C20: Productivité | D20: =IF(D11<>0,D17/D11,0) -> 0.86666667 | E20: =IF(D11<>0,E17/D11,0) -> 0.86666667 | F20: =IF(F11<>0,F17/F11,0) -> 0.84222222 | G20: =IF(F11<>0,G17/F11,0) -> 0.85777778 | H20: =IF(H11<>0,H17/H11,0) -> 0.84555556 | I20: =IF(H11<>0,I17/H11,0) -> 0.85111111 | J20: =IF(J11<>0,J17/J11,0) -> 0.84888889 | K20: =IF(J11<>0,K17/J11,0) -> 0.83777778 | L20: =IF(L11<>0,L17/L11,0) -> 0.83555556 | M20: =IF(L11<>0,M17/L11,0) -> 0.82222222 | N20: =IF(N11<>0,N17/N11,0) -> 0.71444444 | O20: =IF(N11<>0,O17/N11,0) -> 0.68111111
C21: Occupation | D21: =IF(D17<>0,D18/D17,0) -> 0.96153846 | E21: =IF(E17<>0,E18/E17,0) -> 0.96153846 | F21: =IF(F17<>0,F18/F17,0) -> 1.1708443 | G21: =IF(G17<>0,G18/G17,0) -> 1.0362694 | H21: =IF(H17<>0,H18/H17,0) -> 1.027431 | I21: =IF(I17<>0,I18/I17,0) -> 0.98400783 | J21: =IF(J17<>0,J18/J17,0) -> 1.0013089 | K21: =IF(K17<>0,K18/K17,0) -> 1.089191 | ... O21: =IF(O17<>0,O18/O17,0) -> 2.6335644
B22: Nouveau Salarié | C22: Temps disponible (h) | J22: =Paramètres!$C$15 -> 120 | L22: =Paramètres!$C$15 -> 120 | N22: =Paramètres!$C$15 -> 120
C23: Moyen de déplacement | J23: Transports en commun
J24: Prév. | K24: Réel | L24: Prév. | M24: Réel | N24: Prév. | O24: Réel
C25: Déplacement | J25: =VLOOKUP($J$23,Paramètres!$F$14:$G$16,2,FALSE)*J26/60 -> 0.017777778 | K25: =VLOOKUP($J$23,Paramètres!$F$14:$G$16,2,FALSE)*K26/60 -> 1.1955556 | L25: =VLOOKUP($J$23,Paramètres!$F$14:$G$16,2,FALSE)*L26/60 -> 1.4311111 | M25: =VLOOKUP($J$23,Paramètres!$F$14:$G$16,2,FALSE)*M26/60 -> 2.8444444 | N25: =VLOOKUP($J$23,Paramètres!$F$14:$G$16,2,FALSE)*N26/60 -> 14.268889 | O25: =VLOOKUP($J$23,Paramètres!$F$14:$G$16,2,FALSE)*O26/60 -> 17.802222
B26: Administratif | C26: Dépassement capacité Tess | J26: =MAX(-J19,0) -> 0.13333333 | K26: =MAX(-K19,0) -> 8.9666667 | L26: =MAX(-L19,0) -> 10.733333 | M26: =MAX(-M19,0) -> 21.333333 | N26: =MAX(-N19,0) -> 107.01667 | O26: =MAX(-O19,0) -> 133.51667
C27: Perte manque d'engagement | J27: 10 | K27: 0 | L27: 10 | M27: 2 | N27: 2
C28: Temps utilisable cours collectives | J28: =J22-J25-J26-J27 -> 109.84889 | K28: =J22-K25-K26-K27 -> 109.83778 | L28: =L22-L25-L26-L27 -> 97.835556 | M28: =L22-M25-M26-M27 -> 93.822222 | N28: =N22-N25-N26-N27 -> -3.2855556 | O28: =N22-O25-O26-O27 -> -31.318889
B29: Sportif | C29: Séances collectives | J29: =Activité!I17*Activité!I25/60 -> 75 | K29: =Activité!I17*Activité!J25/60 -> 190 | L29: =Activité!K17*Activité!K25/60 -> 165 | M29: =Activité!K17*Activité!L25/60 -> 223.33333 | N29: =Activité!M17*Activité!M25/60 -> 275.16667 | O29: =Activité!M17*Activité!N25/60 -> 301.16667
C30: Restant | J30: =J28-J29 -> 34.848889 | K30: =K28-K29 -> -80.162222 | L30: =L28-L29 -> -67.164444 | M30: =L28-M29 -> -125.49778 | N30: =N28-N29 -> -278.45222 | O30: =N28-O29 -> -304.45222
C31: Productivité | J31: =IF(J22<>0,J28/J22,0) -> 0.91540741 | K31: =IF(J22<>0,K28/J22,0) -> 0.91531481 | L31: =IF(L22<>0,L28/L22,0) -> 0.8152963 | M31: =IF(L22<>0,M28/L22,0) -> 0.78185185 | N31: =IF(N22<>0,N28/N22,0) -> -0.02737963 | O31: =IF(N22<>0,O28/N22,0) -> -0.26099074
C32: Occupation | J32: =IF(J28<>0,J29/J28,0) -> 0.68275611 | K32: =IF(K28<>0,K29/K28,0) -> 1.7298238 | L32: =IF(L28<>0,L29/L28,0) -> 1.6865034 | M32: =IF(M28<>0,M29/M28,0) -> 2.3803884 | N32: =IF(N28<>0,N29/N28,0) -> -83.750423 | O32: =IF(O28<>0,O29/O28,0) -> -9.6161351
A34: Il y des calculs automatiques en place dans les cellules où la police d'écriture est bleue : vous pouvez regarder les calculs en place et les conserver ou les remplacer.

Sheet Paramètres
B1: choisissez | C1: 0
A2: Boisson | B2: eau | C2: 0.5 | F2: Téléphone internet | G2: 50
B3: énergétique | C3: 2 | F3: Expert-comptable | G3: 150
F4: Frais divers | G4: 100
B6: Capital | C6: 8000 | F6: Rémunération | G6: Tess | H6: 2000
G7: Antoine | H7: 600
B8: Taux de TVA | C8: 0.2
F9: Charges TNS | G9: 0.35
B10: Amortissement ordinateur | C10: =1/3 -> 0.33333333 | F10: Charges salariales | G10: 0.23
B11: Amortissement site internet | C11: =1/4 -> 0.25 | F11: Charges patronales | G11: 0.4
F13: Déplacement
A14: Temps | B14: Antoine | C14: 40 | D14: heures | F14: Voiture | G14: 3 | H14: minutes
B15: Tess | C15: 120 | D15: heures | F15: Vélo | G15: 15 | H15: minutes
B16: Brice | C16: 120 | D16: heures | F16: Transports en commun | G16: 8 | H16: minutes
F17: Choisissez
